nonebot_plugin_beatsaberscore/__init__.py
nonebot_plugin_beatsaberscore/api.py
nonebot_plugin_beatsaberscore/cache.py
nonebot_plugin_beatsaberscore/calculation.py
nonebot_plugin_beatsaberscore/config.py
nonebot_plugin_beatsaberscore/corner.py
nonebot_plugin_beatsaberscore/draw.py
nonebot_plugin_beatsaberscore/loading_font.py
nonebot_plugin_beatsaberscore/retry.py
nonebot_plugin_beatsaberscore/static/accuracy.png
nonebot_plugin_beatsaberscore/static/BeatLeader/beatleader.png
nonebot_plugin_beatsaberscore/static/BeatLeader/Easy.png
nonebot_plugin_beatsaberscore/static/BeatLeader/Expert.png
nonebot_plugin_beatsaberscore/static/BeatLeader/ExpertPlus.png
nonebot_plugin_beatsaberscore/static/BeatLeader/Hard.png
nonebot_plugin_beatsaberscore/static/BeatLeader/Normal.png
nonebot_plugin_beatsaberscore/static/bg.png
nonebot_plugin_beatsaberscore/static/blank.png
nonebot_plugin_beatsaberscore/static/highlight.png
nonebot_plugin_beatsaberscore/static/id.png
nonebot_plugin_beatsaberscore/static/rank/a.png
nonebot_plugin_beatsaberscore/static/rank/s.png
nonebot_plugin_beatsaberscore/static/rank/ss.png
nonebot_plugin_beatsaberscore/static/rank/ss_plus.png
nonebot_plugin_beatsaberscore/static/ScoreSaber/Easy.png
nonebot_plugin_beatsaberscore/static/ScoreSaber/Expert.png
nonebot_plugin_beatsaberscore/static/ScoreSaber/ExpertPlus.png
nonebot_plugin_beatsaberscore/static/ScoreSaber/Hard.png
nonebot_plugin_beatsaberscore/static/ScoreSaber/Normal.png
nonebot_plugin_beatsaberscore/static/ScoreSaber/scoresaber.png
nonebot_plugin_beatsaberscore/static/ttf/arial-bold.ttf
nonebot_plugin_beatsaberscore/static/ttf/HanYi.ttf
nonebot_plugin_beatsaberscore/static/ttf/Teko-Bold.ttf
nonebot_plugin_beatsaberscore/storage.py
nonebot_plugin_beatsaberscore-1.4.3.dist-info/LICENSE
nonebot_plugin_beatsaberscore-1.4.3.dist-info/METADATA
nonebot_plugin_beatsaberscore-1.4.3.dist-info/WHEEL
nonebot_plugin_beatsaberscore-1.4.3.dist-info/RECORD
