Metadata-Version: 2.1
Name: nonebot-plugin-beatsaberscore
Version: 1.4.3
Summary: Nonebot2的节奏光剑查分插件,支持BeatLeader&ScoreSaber查分o((>ω< ))o
License: MIT
Author: 12738
Author-email: 12738smp@Gmail.com
Classifier: License :: OSI Approved :: MIT License
Classifier: Programming Language :: Python :: 2
Classifier: Programming Language :: Python :: 2.7
Classifier: Programming Language :: Python :: 3
Classifier: Programming Language :: Python :: 3.4
Classifier: Programming Language :: Python :: 3.5
Classifier: Programming Language :: Python :: 3.6
Classifier: Programming Language :: Python :: 3.7
Classifier: Programming Language :: Python :: 3.8
Classifier: Programming Language :: Python :: 3.9
Classifier: Programming Language :: Python :: 3.10
Classifier: Programming Language :: Python :: 3.11
Classifier: Programming Language :: Python :: 3.12
Requires-Dist: httpx (>=0.22.0)
Requires-Dist: nonebot-adapter-onebot (>=2.0,<3.0)
Requires-Dist: nonebot-plugin-localstore (>=0.7.0)
Requires-Dist: nonebot2 (>=2.2.0)
Requires-Dist: nonebot_plugin_apscheduler (>=0.1.0)
Requires-Dist: pillow (>=9.8.0)
Requires-Dist: pydantic (>=1.10.13)
